_simplextree.cpython-310-darwin.so
_unionfind.cpython-310-darwin.so
simplextree-0.1.0.data/purelib/simplextree/__init__.py
simplextree-0.1.0.data/purelib/simplextree/SimplexTree.py
simplextree-0.1.0.data/purelib/simplextree/UnionFind.py
simplextree-0.1.0.dist-info/RECORD
simplextree-0.1.0.dist-info/LICENSE
simplextree-0.1.0.dist-info/WHEEL
simplextree-0.1.0.dist-info/METADATA
