Metadata-Version: 2.1
Name: simplextree
Version: 0.1.0
Author-Email: Matt Piekenbrock <matt.piekenbrock@gmail.com>
License:                                  Apache License
Classifier: Intended Audience :: Science/Research
Classifier: Development Status :: 3 - Alpha
Classifier: License :: OSI Approved :: Apache Software License
Classifier: Programming Language :: Python :: 3
Project-URL: Homepage, https://github.com/peekxc/simplextree-py
Project-URL: Repository, https://github.com/peekxc/simplextree-py
Project-URL: Changelog, https://github.com/peekxc/simplextree-py/blob/main/CHANGELOG.md
Requires-Python: >=3.8
Requires-Dist: numpy
Requires-Dist: scipy
Requires-Dist: more_itertools
Requires-Dist: ruff; extra == "dev"
Requires-Dist: mypy<1.6,>=1.0; extra == "dev"
Requires-Dist: black<24.0,>=23.0; extra == "dev"
Requires-Dist: isort<5.13,>=5.12; extra == "dev"
Requires-Dist: pytest; extra == "dev"
Requires-Dist: pytest-cov; extra == "dev"
Requires-Dist: twine>=1.11.0; extra == "dev"
Requires-Dist: build; extra == "dev"
Requires-Dist: setuptools; extra == "dev"
Requires-Dist: wheel; extra == "dev"
Requires-Dist: packaging; extra == "dev"
Provides-Extra: dev
